setconf.py
setconf-0.7.4.dist-info/DESCRIPTION.rst
setconf-0.7.4.dist-info/METADATA
setconf-0.7.4.dist-info/RECORD
setconf-0.7.4.dist-info/WHEEL
setconf-0.7.4.dist-info/entry_points.txt
setconf-0.7.4.dist-info/metadata.json
setconf-0.7.4.dist-info/top_level.txt
