Metadata-Version: 2.0
Name: setconf
Version: 0.7.4
Summary: Change configuration settings in text files
Home-page: http://setconf.roboticoverlords.org/
Author: Alexander F Rødseth
Author-email: xyproto@archlinux.org
License: GPLv2
Platform: UNKNOWN
Classifier: Environment :: Console
Classifier: License :: OSI Approved :: GNU General Public License v2 (GPLv2)
Classifier: Programming Language :: Python
Classifier: Topic :: System :: Shells
Classifier: Topic :: Utilities
